load_dotenv.pth
load_dotenv.py
load_dotenv-0.1.0.dist-info/LICENSE
load_dotenv-0.1.0.dist-info/METADATA
load_dotenv-0.1.0.dist-info/WHEEL
load_dotenv-0.1.0.dist-info/top_level.txt
load_dotenv-0.1.0.dist-info/RECORD
