Metadata-Version: 2.1
Name: load-dotenv
Version: 0.1.0
Summary: Automatically and implicitly load environment variables from .env file
Home-page: https://github.com/fly/load-dotenv
Author: fly
Project-URL: Source, https://github.com/fly/load-dotenv
Project-URL: Tracker, https://github.com/fly/load-dotenv/issues
Keywords: environment variables,env,.env,dotenv
Classifier: Development Status :: 4 - Beta
Classifier: Intended Audience :: Developers
Classifier: Topic :: Software Development
Classifier: License :: OSI Approved :: Apache Software License
Classifier: Programming Language :: Python :: 3
License-File: LICENSE
